langchain_surrealdb/__init__.py
langchain_surrealdb/py.typed
langchain_surrealdb/utils.py
langchain_surrealdb/vectorstores.py
langchain_surrealdb/experimental/__init__.py
langchain_surrealdb/experimental/surrealdb_graph.py
langchain_surrealdb/experimental/graph_qa/__init__.py
langchain_surrealdb/experimental/graph_qa/chain.py
langchain_surrealdb/experimental/graph_qa/prompts.py
langchain_surrealdb-0.2.0.dist-info/licenses/LICENSE
langchain_surrealdb-0.2.0.dist-info/METADATA
langchain_surrealdb-0.2.0.dist-info/WHEEL
langchain_surrealdb-0.2.0.dist-info/top_level.txt
langchain_surrealdb-0.2.0.dist-info/RECORD
