Metadata-Version: 2.4
Name: langchain_surrealdb
Version: 0.2.0
Summary: An integration package connecting SurrealDB and LangChain
License-Expression: MIT
Project-URL: homepage, https://surrealdb.com/docs/integrations/frameworks/langchain
Project-URL: documentation, https://surrealdb.com/docs/integrations/frameworks/langchain
Project-URL: source, https://github.com/surrealdb/langchain-surrealdb
Project-URL: changelog, https://github.com/surrealdb/langchain-surrealdb/blob/main/CHANGELOG.md
Requires-Python: <4.0,>=3.10
License-File: LICENSE
Requires-Dist: langchain-core~=1.1.0
Requires-Dist: surrealdb~=1.0.7
Dynamic: license-file
